tikapipy/__init__.py
tikapipy/tik.py
tikapipy-1.1.7.dist-info/METADATA
tikapipy-1.1.7.dist-info/WHEEL
tikapipy-1.1.7.dist-info/top_level.txt
tikapipy-1.1.7.dist-info/RECORD
