Metadata-Version: 2.1
Name: tikapipy
Version: 1.1.7
Summary: An api-wrapper for https://tiktok.jiroawesome.tech/.
Home-page: https://github.com/jiroawesome/tikapipy
Author: jiroawesome
License: UNKNOWN
Project-URL: Bug Tracker, https://github.com/jiroawesome/tikapipy/issues
Platform: UNKNOWN
Classifier: Programming Language :: Python :: 3
Classifier: License :: OSI Approved :: MIT License
Classifier: Operating System :: OS Independent
Requires-Python: >=3.6
Requires-Dist: requests
